RKA/__init__.py
RKA/keep_alive.py
rka-0.0.2.dist-info/METADATA
rka-0.0.2.dist-info/WHEEL
rka-0.0.2.dist-info/licenses/LICENSE
rka-0.0.2.dist-info/RECORD
