Metadata-Version: 2.1
Name: RKA
Version: 0.0.2
Summary: Keeps your replit app running
Project-URL: Homepage, https://github.com/Reathe/RKA
Project-URL: Bug Tracker, https://github.com/Reathe/RKA/issues
Author-email: Rafael Bachourian <bachourian@gmail.com>
License-File: LICENSE
Classifier: License :: OSI Approved :: MIT License
Classifier: Operating System :: OS Independent
Classifier: Programming Language :: Python :: 3
Requires-Python: >=3.8
Requires-Dist: flask~=2.3
Provides-Extra: dev
Requires-Dist: black~=23.9; extra == 'dev'
Requires-Dist: flake8~=6.1; extra == 'dev'
Requires-Dist: isort~=5.12; extra == 'dev'
Requires-Dist: mypy~=1.5; extra == 'dev'
Requires-Dist: pytest~=7.4; extra == 'dev'
Requires-Dist: tox~=4.11; extra == 'dev'
